{
    "title": "123",
    "listOfQuestions": [
        {
            "question": "What is 5254 / 71?",
            "correctAnswer": 74,
            "wrongAnswers": [
                80,
                81,
                84
            ],
            "timeout": 15
        },
        {
            "question": "What is 7 + 10?",
            "correctAnswer": 17,
            "wrongAnswers": [
                12,
                21,
                22
            ],
            "timeout": 15
        },
        {
            "question": "What is the square root of 144?",
            "correctAnswer": 12,
            "wrongAnswers": [
                10,
                13,
                6
            ],
            "timeout": 15
        },
        {
            "question": "What is 5^2?",
            "correctAnswer": 25,
            "wrongAnswers": [
                29,
                30,
                31
            ],
            "timeout": 15
        },
        {
            "question": "What is 43 + 16?",
            "correctAnswer": 59,
            "wrongAnswers": [
                64,
                49,
                67
            ],
            "timeout": 15
        },
        {
            "question": "What is 26 + 23?",
            "correctAnswer": 49,
            "wrongAnswers": [
                42,
                52,
                53
            ],
            "timeout": 15
        },
        {
            "question": "What is 86 + 31?",
            "correctAnswer": 117,
            "wrongAnswers": [
                121,
                118,
                127
            ],
            "timeout": 15
        },
        {
            "question": "What is the square root of 144?",
            "correctAnswer": 12,
            "wrongAnswers": [
                16,
                9,
                7
            ],
            "timeout": 15
        },
        {
            "question": "What is 4^2?",
            "correctAnswer": 16,
            "wrongAnswers": [
                25,
                11,
                22
            ],
            "timeout": 15
        },
        {
            "question": "What is 59 * 13?",
            "correctAnswer": 767,
            "wrongAnswers": [
                763,
                772,
                766
            ],
            "timeout": 15
        },
        {
            "question": "What is the square root of 4?",
            "correctAnswer": 2,
            "wrongAnswers": [
                3,
                11,
                12
            ],
            "timeout": 15
        },
        {
            "question": "What is 3^5?",
            "correctAnswer": 243,
            "wrongAnswers": [
                252,
                236,
                245
            ],
            "timeout": 15
        },
        {
            "question": "What is 6!?",
            "correctAnswer": 720,
            "wrongAnswers": [
                722,
                724,
                719
            ],
            "timeout": 15
        },
        {
            "question": "What is 1584 / 88?",
            "correctAnswer": 18,
            "wrongAnswers": [
                24,
                26,
                13
            ],
            "timeout": 15
        },
        {
            "question": "What is 15 - 27?",
            "correctAnswer": -12,
            "wrongAnswers": [
                -14,
                -21,
                -5
            ],
            "timeout": 15
        },
        {
            "question": "What is 78 * 4?",
            "correctAnswer": 312,
            "wrongAnswers": [
                313,
                307,
                318
            ],
            "timeout": 15
        },
        {
            "question": "What is 40 / 4?",
            "correctAnswer": 10,
            "wrongAnswers": [
                0,
                2,
                20
            ],
            "timeout": 15
        },
        {
            "question": "What is the square root of 36?",
            "correctAnswer": 6,
            "wrongAnswers": [
                8,
                4,
                -2
            ],
            "timeout": 15
        },
        {
            "question": "What is 1134 / 27?",
            "correctAnswer": 42,
            "wrongAnswers": [
                41,
                34,
                33
            ],
            "timeout": 15
        },
        {
            "question": "What is 53 + 11?",
            "correctAnswer": 64,
            "wrongAnswers": [
                72,
                60,
                68
            ],
            "timeout": 15
        },
        {
            "question": "What is 3!?",
            "correctAnswer": 6,
            "wrongAnswers": [
                1,
                -3,
                13
            ],
            "timeout": 15
        },
        {
            "question": "What is 1008 / 63?",
            "correctAnswer": 16,
            "wrongAnswers": [
                8,
                13,
                15
            ],
            "timeout": 15
        },
        {
            "question": "What is 91 + 23?",
            "correctAnswer": 114,
            "wrongAnswers": [
                104,
                108,
                117
            ],
            "timeout": 15
        },
        {
            "question": "What is 702 / 78?",
            "correctAnswer": 9,
            "wrongAnswers": [
                0,
                -1,
                14
            ],
            "timeout": 15
        },
        {
            "question": "What is 30 - 79?",
            "correctAnswer": -49,
            "wrongAnswers": [
                -59,
                -42,
                -41
            ],
            "timeout": 15
        },
        {
            "question": "What is 4^5?",
            "correctAnswer": 1024,
            "wrongAnswers": [
                1019,
                1014,
                1022
            ],
            "timeout": 15
        },
        {
            "question": "What is the square root of 144?",
            "correctAnswer": 12,
            "wrongAnswers": [
                8,
                3,
                14
            ],
            "timeout": 15
        },
        {
            "question": "What is the square root of 36?",
            "correctAnswer": 6,
            "wrongAnswers": [
                4,
                13,
                14
            ],
            "timeout": 15
        },
        {
            "question": "What is 6!?",
            "correctAnswer": 720,
            "wrongAnswers": [
                712,
                714,
                728
            ],
            "timeout": 15
        },
        {
            "question": "What is 64 * 91?",
            "correctAnswer": 5824,
            "wrongAnswers": [
                5833,
                5827,
                5823
            ],
            "timeout": 15
        },
        {
            "question": "What is 5^2?",
            "correctAnswer": 25,
            "wrongAnswers": [
                33,
                19,
                31
            ],
            "timeout": 15
        },
        {
            "question": "What is 104 / 2?",
            "correctAnswer": 52,
            "wrongAnswers": [
                51,
                59,
                47
            ],
            "timeout": 15
        },
        {
            "question": "What is 935 / 11?",
            "correctAnswer": 85,
            "wrongAnswers": [
                82,
                94,
                87
            ],
            "timeout": 15
        },
        {
            "question": "What is 60 - 71?",
            "correctAnswer": -11,
            "wrongAnswers": [
                -8,
                -14,
                -18
            ],
            "timeout": 15
        },
        {
            "question": "What is the square root of 100?",
            "correctAnswer": 10,
            "wrongAnswers": [
                0,
                16,
                1
            ],
            "timeout": 15
        },
        {
            "question": "What is 1^2?",
            "correctAnswer": 1,
            "wrongAnswers": [
                0,
                -4,
                -9
            ],
            "timeout": 15
        },
        {
            "question": "What is the square root of 4?",
            "correctAnswer": 2,
            "wrongAnswers": [
                1,
                -7,
                -1
            ],
            "timeout": 15
        },
        {
            "question": "What is 1264 / 79?",
            "correctAnswer": 16,
            "wrongAnswers": [
                11,
                13,
                14
            ],
            "timeout": 15
        },
        {
            "question": "What is 77 * 14?",
            "correctAnswer": 1078,
            "wrongAnswers": [
                1072,
                1079,
                1071
            ],
            "timeout": 15
        },
        {
            "question": "What is 54 * 18?",
            "correctAnswer": 972,
            "wrongAnswers": [
                976,
                964,
                965
            ],
            "timeout": 15
        },
        {
            "question": "What is 4!?",
            "correctAnswer": 24,
            "wrongAnswers": [
                25,
                27,
                30
            ],
            "timeout": 15
        },
        {
            "question": "What is 32 + 69?",
            "correctAnswer": 101,
            "wrongAnswers": [
                104,
                103,
                111
            ],
            "timeout": 15
        },
        {
            "question": "What is the square root of 100?",
            "correctAnswer": 10,
            "wrongAnswers": [
                0,
                1,
                8
            ],
            "timeout": 15
        },
        {
            "question": "What is 4^4?",
            "correctAnswer": 256,
            "wrongAnswers": [
                251,
                260,
                263
            ],
            "timeout": 15
        },
        {
            "question": "What is 24 * 44?",
            "correctAnswer": 1056,
            "wrongAnswers": [
                1057,
                1050,
                1055
            ],
            "timeout": 15
        },
        {
            "question": "What is 2^3?",
            "correctAnswer": 8,
            "wrongAnswers": [
                17,
                10,
                7
            ],
            "timeout": 15
        },
        {
            "question": "What is 5^2?",
            "correctAnswer": 25,
            "wrongAnswers": [
                31,
                28,
                15
            ],
            "timeout": 15
        },
        {
            "question": "What is 38 - 78?",
            "correctAnswer": -40,
            "wrongAnswers": [
                -37,
                -50,
                -41
            ],
            "timeout": 15
        },
        {
            "question": "What is 5037 / 69?",
            "correctAnswer": 73,
            "wrongAnswers": [
                63,
                70,
                79
            ],
            "timeout": 15
        },
        {
            "question": "What is 2415 / 69?",
            "correctAnswer": 35,
            "wrongAnswers": [
                45,
                37,
                39
            ],
            "timeout": 15
        },
        {
            "question": "What is the square root of 4?",
            "correctAnswer": 2,
            "wrongAnswers": [
                9,
                12,
                -7
            ],
            "timeout": 15
        },
        {
            "question": "What is 6^6?",
            "correctAnswer": 46656,
            "wrongAnswers": [
                46664,
                46659,
                46661
            ],
            "timeout": 15
        },
        {
            "question": "What is 25 * 89?",
            "correctAnswer": 2225,
            "wrongAnswers": [
                2217,
                2233,
                2235
            ],
            "timeout": 15
        },
        {
            "question": "What is 3!?",
            "correctAnswer": 6,
            "wrongAnswers": [
                2,
                -1,
                7
            ],
            "timeout": 15
        },
        {
            "question": "What is 5!?",
            "correctAnswer": 120,
            "wrongAnswers": [
                122,
                124,
                126
            ],
            "timeout": 15
        },
        {
            "question": "What is 59 + 73?",
            "correctAnswer": 132,
            "wrongAnswers": [
                129,
                122,
                126
            ],
            "timeout": 15
        },
        {
            "question": "What is 85 * 71?",
            "correctAnswer": 6035,
            "wrongAnswers": [
                6041,
                6029,
                6038
            ],
            "timeout": 15
        },
        {
            "question": "What is the square root of 16?",
            "correctAnswer": 4,
            "wrongAnswers": [
                8,
                -5,
                -3
            ],
            "timeout": 15
        },
        {
            "question": "What is the square root of 4?",
            "correctAnswer": 2,
            "wrongAnswers": [
                -7,
                6,
                1
            ],
            "timeout": 15
        },
        {
            "question": "What is 3984 / 48?",
            "correctAnswer": 83,
            "wrongAnswers": [
                73,
                82,
                86
            ],
            "timeout": 15
        },
        {
            "question": "What is the square root of 4?",
            "correctAnswer": 2,
            "wrongAnswers": [
                -6,
                3,
                -4
            ],
            "timeout": 15
        },
        {
            "question": "What is 18 * 23?",
            "correctAnswer": 414,
            "wrongAnswers": [
                419,
                404,
                406
            ],
            "timeout": 15
        },
        {
            "question": "What is 13 * 27?",
            "correctAnswer": 351,
            "wrongAnswers": [
                347,
                356,
                341
            ],
            "timeout": 15
        },
        {
            "question": "What is 1260 / 30?",
            "correctAnswer": 42,
            "wrongAnswers": [
                40,
                35,
                46
            ],
            "timeout": 15
        },
        {
            "question": "What is 6^5?",
            "correctAnswer": 7776,
            "wrongAnswers": [
                7768,
                7777,
                7770
            ],
            "timeout": 15
        },
        {
            "question": "What is 6^2?",
            "correctAnswer": 36,
            "wrongAnswers": [
                40,
                26,
                28
            ],
            "timeout": 15
        },
        {
            "question": "What is 324 / 36?",
            "correctAnswer": 9,
            "wrongAnswers": [
                17,
                11,
                12
            ],
            "timeout": 15
        },
        {
            "question": "What is 21 * 75?",
            "correctAnswer": 1575,
            "wrongAnswers": [
                1584,
                1573,
                1583
            ],
            "timeout": 15
        },
        {
            "question": "What is 6642 / 81?",
            "correctAnswer": 82,
            "wrongAnswers": [
                72,
                81,
                79
            ],
            "timeout": 15
        },
        {
            "question": "What is 17 + 53?",
            "correctAnswer": 70,
            "wrongAnswers": [
                68,
                62,
                76
            ],
            "timeout": 15
        },
        {
            "question": "What is the square root of 4?",
            "correctAnswer": 2,
            "wrongAnswers": [
                9,
                12,
                5
            ],
            "timeout": 15
        },
        {
            "question": "What is 33 - 31?",
            "correctAnswer": 2,
            "wrongAnswers": [
                1,
                -5,
                -3
            ],
            "timeout": 15
        },
        {
            "question": "What is 8930 / 95?",
            "correctAnswer": 94,
            "wrongAnswers": [
                99,
                86,
                103
            ],
            "timeout": 15
        },
        {
            "question": "What is 4!?",
            "correctAnswer": 24,
            "wrongAnswers": [
                32,
                29,
                22
            ],
            "timeout": 15
        },
        {
            "question": "What is the square root of 16?",
            "correctAnswer": 4,
            "wrongAnswers": [
                2,
                5,
                6
            ],
            "timeout": 15
        },
        {
            "question": "What is 57 * 38?",
            "correctAnswer": 2166,
            "wrongAnswers": [
                2173,
                2165,
                2175
            ],
            "timeout": 15
        },
        {
            "question": "What is 405 / 9?",
            "correctAnswer": 45,
            "wrongAnswers": [
                48,
                44,
                53
            ],
            "timeout": 15
        },
        {
            "question": "What is 3848 / 52?",
            "correctAnswer": 74,
            "wrongAnswers": [
                81,
                67,
                76
            ],
            "timeout": 15
        },
        {
            "question": "What is 55 - 75?",
            "correctAnswer": -20,
            "wrongAnswers": [
                -21,
                -18,
                -26
            ],
            "timeout": 15
        },
        {
            "question": "What is 1!?",
            "correctAnswer": 1,
            "wrongAnswers": [
                0,
                -6,
                5
            ],
            "timeout": 15
        },
        {
            "question": "What is the square root of 4?",
            "correctAnswer": 2,
            "wrongAnswers": [
                12,
                6,
                -2
            ],
            "timeout": 15
        },
        {
            "question": "What is 7 - 56?",
            "correctAnswer": -49,
            "wrongAnswers": [
                -51,
                -59,
                -50
            ],
            "timeout": 15
        },
        {
            "question": "What is the square root of 64?",
            "correctAnswer": 8,
            "wrongAnswers": [
                18,
                4,
                -1
            ],
            "timeout": 15
        },
        {
            "question": "What is 1^5?",
            "correctAnswer": 1,
            "wrongAnswers": [
                -7,
                -1,
                7
            ],
            "timeout": 15
        },
        {
            "question": "What is 6272 / 64?",
            "correctAnswer": 98,
            "wrongAnswers": [
                90,
                106,
                103
            ],
            "timeout": 15
        },
        {
            "question": "What is 5394 / 62?",
            "correctAnswer": 87,
            "wrongAnswers": [
                91,
                92,
                78
            ],
            "timeout": 15
        },
        {
            "question": "What is 4!?",
            "correctAnswer": 24,
            "wrongAnswers": [
                25,
                26,
                21
            ],
            "timeout": 15
        },
        {
            "question": "What is 40 * 47?",
            "correctAnswer": 1880,
            "wrongAnswers": [
                1886,
                1877,
                1870
            ],
            "timeout": 15
        },
        {
            "question": "What is 492 / 6?",
            "correctAnswer": 82,
            "wrongAnswers": [
                88,
                89,
                83
            ],
            "timeout": 15
        },
        {
            "question": "What is 2142 / 34?",
            "correctAnswer": 63,
            "wrongAnswers": [
                60,
                69,
                55
            ],
            "timeout": 15
        },
        {
            "question": "What is 2!?",
            "correctAnswer": 2,
            "wrongAnswers": [
                -8,
                11,
                4
            ],
            "timeout": 15
        },
        {
            "question": "What is 7220 / 76?",
            "correctAnswer": 95,
            "wrongAnswers": [
                101,
                93,
                85
            ],
            "timeout": 15
        },
        {
            "question": "What is the square root of 16?",
            "correctAnswer": 4,
            "wrongAnswers": [
                10,
                13,
                -1
            ],
            "timeout": 15
        },
        {
            "question": "What is 61 * 16?",
            "correctAnswer": 976,
            "wrongAnswers": [
                973,
                981,
                968
            ],
            "timeout": 15
        },
        {
            "question": "What is 3!?",
            "correctAnswer": 6,
            "wrongAnswers": [
                11,
                5,
                -2
            ],
            "timeout": 15
        },
        {
            "question": "What is 1178 / 62?",
            "correctAnswer": 19,
            "wrongAnswers": [
                10,
                26,
                14
            ],
            "timeout": 15
        },
        {
            "question": "What is 88 / 2?",
            "correctAnswer": 44,
            "wrongAnswers": [
                43,
                35,
                45
            ],
            "timeout": 15
        },
        {
            "question": "What is 79 + 13?",
            "correctAnswer": 92,
            "wrongAnswers": [
                89,
                97,
                101
            ],
            "timeout": 15
        },
        {
            "question": "What is 29 - 34?",
            "correctAnswer": -5,
            "wrongAnswers": [
                0,
                1,
                -10
            ],
            "timeout": 15
        },
        {
            "question": "What is 6!?",
            "correctAnswer": 720,
            "wrongAnswers": [
                713,
                722,
                718
            ],
            "timeout": 15
        },
        {
            "question": "What is 50 * 3?",
            "correctAnswer": 150,
            "wrongAnswers": [
                153,
                142,
                159
            ],
            "timeout": 15
        },
        {
            "question": "What is 2^4?",
            "correctAnswer": 16,
            "wrongAnswers": [
                25,
                6,
                17
            ],
            "timeout": 15
        },
        {
            "question": "What is 62 + 60?",
            "correctAnswer": 122,
            "wrongAnswers": [
                120,
                121,
                118
            ],
            "timeout": 15
        },
        {
            "question": "What is 5!?",
            "correctAnswer": 120,
            "wrongAnswers": [
                130,
                125,
                117
            ],
            "timeout": 15
        },
        {
            "question": "What is 4^4?",
            "correctAnswer": 256,
            "wrongAnswers": [
                251,
                260,
                261
            ],
            "timeout": 15
        },
        {
            "question": "What is 5^6?",
            "correctAnswer": 15625,
            "wrongAnswers": [
                15635,
                15629,
                15615
            ],
            "timeout": 15
        },
        {
            "question": "What is the square root of 36?",
            "correctAnswer": 6,
            "wrongAnswers": [
                8,
                16,
                -1
            ],
            "timeout": 15
        },
        {
            "question": "What is 5!?",
            "correctAnswer": 120,
            "wrongAnswers": [
                122,
                110,
                114
            ],
            "timeout": 15
        },
        {
            "question": "What is the square root of 64?",
            "correctAnswer": 8,
            "wrongAnswers": [
                11,
                -2,
                -1
            ],
            "timeout": 15
        },
        {
            "question": "What is 252 / 6?",
            "correctAnswer": 42,
            "wrongAnswers": [
                51,
                36,
                38
            ],
            "timeout": 15
        },
        {
            "question": "What is 2^2?",
            "correctAnswer": 4,
            "wrongAnswers": [
                8,
                5,
                -3
            ],
            "timeout": 15
        },
        {
            "question": "What is the square root of 36?",
            "correctAnswer": 6,
            "wrongAnswers": [
                1,
                -4,
                7
            ],
            "timeout": 15
        },
        {
            "question": "What is 34 * 89?",
            "correctAnswer": 3026,
            "wrongAnswers": [
                3021,
                3033,
                3029
            ],
            "timeout": 15
        },
        {
            "question": "What is 2^2?",
            "correctAnswer": 4,
            "wrongAnswers": [
                10,
                12,
                13
            ],
            "timeout": 15
        },
        {
            "question": "What is 86 - 57?",
            "correctAnswer": 29,
            "wrongAnswers": [
                36,
                21,
                22
            ],
            "timeout": 15
        },
        {
            "question": "What is the square root of 4?",
            "correctAnswer": 2,
            "wrongAnswers": [
                0,
                1,
                12
            ],
            "timeout": 15
        },
        {
            "question": "What is 289 / 17?",
            "correctAnswer": 17,
            "wrongAnswers": [
                27,
                21,
                7
            ],
            "timeout": 15
        },
        {
            "question": "What is 100 * 67?",
            "correctAnswer": 6700,
            "wrongAnswers": [
                6698,
                6707,
                6701
            ],
            "timeout": 15
        },
        {
            "question": "What is 44 / 44?",
            "correctAnswer": 1,
            "wrongAnswers": [
                11,
                -3,
                -1
            ],
            "timeout": 15
        },
        {
            "question": "What is 5846 / 79?",
            "correctAnswer": 74,
            "wrongAnswers": [
                75,
                70,
                71
            ],
            "timeout": 15
        },
        {
            "question": "What is 470 / 5?",
            "correctAnswer": 94,
            "wrongAnswers": [
                90,
                92,
                103
            ],
            "timeout": 15
        },
        {
            "question": "What is the square root of 4?",
            "correctAnswer": 2,
            "wrongAnswers": [
                1,
                -7,
                9
            ],
            "timeout": 15
        },
        {
            "question": "What is the square root of 16?",
            "correctAnswer": 4,
            "wrongAnswers": [
                9,
                10,
                14
            ],
            "timeout": 15
        }
    ],
    "time given": 15
}