{"title": "Scouting", "difficulty": 3, "randomOrder": false, "listOfQuestions": [{"question": "What is the main purpose of scouting?", "correctAnswer": "To teach youth skills and values", "wrongAnswers": ["To prepare for military service", "To promote competition", "To focus solely on outdoor activities"], "timeout": 15}, {"question": "Which organization was founded by Robert Baden-Powell?", "correctAnswer": "Boy Scouts", "wrongAnswers": ["Girl Scouts", "4-H Club", "Campfire"], "timeout": 15}, {"question": "What is the Scout Oath?", "correctAnswer": "An oath that outlines a scout's commitment to duty, service, and moral character", "wrongAnswers": ["A pledge to always win", "A promise to follow all rules", "A commitment to outdoor living"], "timeout": 15}, {"question": "What does the 'Be Prepared' motto of scouting emphasize?", "correctAnswer": "Readiness for any situation", "wrongAnswers": ["Winning competitions", "Avoiding risks", "Following orders"], "timeout": 15}, {"question": "In which year was the Boy Scouts of America founded?", "correctAnswer": "1910", "wrongAnswers": ["1905", "1915", "1920"], "timeout": 15}, {"question": "What is the official flower of the Girl Scouts?", "correctAnswer": "The green and white carnation", "wrongAnswers": ["Rose", "Sunflower", "Daisy"], "timeout": 15}, {"question": "What are the three parts of the Scout Law?", "correctAnswer": "Trustworthy, loyal, helpful", "wrongAnswers": ["Brave, strong, wise", "Honest, kind, respectful", "Fair, friendly, cheerful"], "timeout": 15}, {"question": "What is the highest rank a Boy Scout can achieve?", "correctAnswer": "Eagle Scout", "wrongAnswers": ["Life Scout", "Star Scout", "Tenderfoot"], "timeout": 15}, {"question": "Which outdoor skill is NOT typically taught in scouting?", "correctAnswer": "Skydiving", "wrongAnswers": ["Camping", "Hiking", "First aid"], "timeout": 15}, {"question": "What does the color blue represent in the Boy Scouts?", "correctAnswer": "Truth and loyalty", "wrongAnswers": ["Friendship", "Adventure", "Leadership"], "timeout": 15}, {"question": "What is the primary age range for Cub Scouts?", "correctAnswer": "7 to 10 years old", "wrongAnswers": ["5 to 7 years old", "10 to 13 years old", "13 to 18 years old"], "timeout": 15}, {"question": "Which type of scouting is focused on younger girls?", "correctAnswer": "Brownies", "wrongAnswers": ["Cadettes", "Seniors", "Ambassadors"], "timeout": 15}, {"question": "What is the significance of the Scout handshake?", "correctAnswer": "A symbol of friendship and trust among scouts", "wrongAnswers": ["A secret code", "A form of greeting only for leaders", "A way to show respect"], "timeout": 15}, {"question": "Which scouting group focuses on STEM activities?", "correctAnswer": "Explorers", "wrongAnswers": ["Venturers", "Cub Scouts", "Brownies"], "timeout": 15}, {"question": "What is one of the key benefits of scouting?", "correctAnswer": "Development of leadership skills", "wrongAnswers": ["Building personal wealth", "Competition with others", "Focus on individual achievements"], "timeout": 15}, {"question": "The Girl Scouts was founded in what year?", "correctAnswer": "1912", "wrongAnswers": ["1900", "1920", "1930"], "timeout": 15}, {"question": "What does the Scout motto 'Do a Good Turn Daily' encourage scouts to do?", "correctAnswer": "Perform acts of kindness for others", "wrongAnswers": ["Complete tasks quickly", "Win competitions", "Focus on self-improvement"], "timeout": 15}, {"question": "What is the primary focus of Venturing in scouting?", "correctAnswer": "Leadership and personal growth", "wrongAnswers": ["Merit badge completion", "Outdoor survival", "Community service only"], "timeout": 15}, {"question": "Which activity is commonly associated with scouting?", "correctAnswer": "Camping", "wrongAnswers": ["Shopping", "Video gaming", "Traveling internationally"], "timeout": 15}, {"question": "What is the significance of the Scout uniform?", "correctAnswer": "It represents unity and belonging", "wrongAnswers": ["It indicates rank only", "It's a fashion statement", "It's required for all activities"], "timeout": 15}, {"question": "What is the primary goal of the Outdoor Code?", "correctAnswer": "To encourage respect for nature and the environment", "wrongAnswers": ["To ensure safety only", "To promote competition in outdoor skills", "To limit outdoor activities"], "timeout": 15}, {"question": "What is the symbol of the Boy Scouts?", "correctAnswer": "The Fleur-de-lis", "wrongAnswers": ["The Eagle", "The Compass", "The Oak Leaf"], "timeout": 15}, {"question": "What do scouts learn about through first aid training?", "correctAnswer": "How to respond to emergencies", "wrongAnswers": ["How to cook meals", "How to build shelters", "How to navigate using stars"], "timeout": 15}, {"question": "What is the significance of the Scout's 'wood badge'?", "correctAnswer": "It signifies advanced leadership training", "wrongAnswers": ["It indicates completion of all badges", "It is a reward for participation", "It is a ceremonial item only"], "timeout": 15}, {"question": "Which camping style is often encouraged in scouting?", "correctAnswer": "Leave No Trace", "wrongAnswers": ["Glamping", "Survival camping", "Backpacking only"], "timeout": 15}, {"question": "Which of the following is NOT a method of scouting?", "correctAnswer": "Extensive travel", "wrongAnswers": ["Outdoor activities", "Community service", "Leadership training"], "timeout": 15}, {"question": "What is the main focus of the Order of the Arrow?", "correctAnswer": "Honor and service to others", "wrongAnswers": ["Competition and winning", "Outdoor survival skills", "Merit badge completion"], "timeout": 15}, {"question": "What are 'Wood Badge beads' awarded for?", "correctAnswer": "Completing advanced training in leadership", "wrongAnswers": ["Winning competitions", "Merit badge achievements", "Community service"], "timeout": 15}, {"question": "What does the 'Scout Spirit' encourage?", "correctAnswer": "Living by the principles of scouting", "wrongAnswers": ["Winning at all costs", "Ignoring rules", "Focusing only on personal goals"], "timeout": 15}, {"question": "Which of these is an important skill taught in scouting?", "correctAnswer": "Navigation", "wrongAnswers": ["Public speaking", "Advanced mathematics", "Cooking gourmet meals"], "timeout": 15}, {"question": "What does it mean to 'camp under the stars'?", "correctAnswer": "Camping without a tent", "wrongAnswers": ["Camping only in winter", "Camping with luxury amenities", "Camping with no food"], "timeout": 15}, {"question": "What is the primary age group for Scouts BSA?", "correctAnswer": "11 to 17 years old", "wrongAnswers": ["5 to 10 years old", "10 to 14 years old", "18 and older"], "timeout": 15}, {"question": "What is a common service project for scouts?", "correctAnswer": "Cleaning up parks", "wrongAnswers": ["Organizing competitions", "Building commercial buildings", "Starting a business"], "timeout": 15}, {"question": "What is the motto of the Girl Scouts?", "correctAnswer": "Be prepared", "wrongAnswers": ["Always win", "Do your best", "Work hard"], "timeout": 15}, {"question": "What is the primary role of adult leaders in scouting?", "correctAnswer": "To mentor and guide youth", "wrongAnswers": ["To control all activities", "To compete with youth", "To plan all events without input"], "timeout": 15}]}